buienalarm/__init__.py
buienalarm/cli.py
buienalarm/py.typed
buienalarm/pybuienalarm.py
pybuienalarm-0.1.1.dist-info/LICENSE
pybuienalarm-0.1.1.dist-info/METADATA
pybuienalarm-0.1.1.dist-info/WHEEL
pybuienalarm-0.1.1.dist-info/entry_points.txt
pybuienalarm-0.1.1.dist-info/top_level.txt
pybuienalarm-0.1.1.dist-info/RECORD
