Metadata-Version: 2.1
Name: pybuienalarm
Version: 0.1.1
Summary: Simple API to access Buienalarm data.
Home-page: https://github.com/gieljnssns/buienalarm
Author: Giel Janssens
Author-email: gieljnssns@vivaldi.net
License: MIT
Platform: UNKNOWN
License-File: LICENSE
Requires-Dist: requests
